searchPrimo/__init__.py
searchPrimo-1.0.dist-info/LICENSE
searchPrimo-1.0.dist-info/METADATA
searchPrimo-1.0.dist-info/WHEEL
searchPrimo-1.0.dist-info/top_level.txt
searchPrimo-1.0.dist-info/RECORD
