Metadata-Version: 2.1
Name: searchPrimo
Version: 1.0
Summary: Operaciones para encontrar los numeros primos.
Home-page: UNKNOWN
Author: Antonio Pinar
Author-email: antoniopinar2@gmail.com
License: GNU GPLv3
Keywords: pyoperaciones mathematical operations primo
Platform: UNKNOWN
Classifier: Development Status :: 4 - Beta
Classifier: Intended Audience :: Developers
Classifier: Topic :: Utilities
Classifier: License :: OSI Approved :: GNU General Public License v3 (GPLv3)
Classifier: Programming Language :: Python :: 3
Classifier: Operating System :: OS Independent
License-File: LICENSE
